pikvm_lib/__init__.py
pikvm_lib/keymaps.py
pikvm_lib/pikvm.py
pikvm_lib/pikvm_atx.py
pikvm_lib/pikvm_gpio.py
pikvm_lib/pikvm_keyboard.py
pikvm_lib/pikvm_mouse.py
pikvm_lib/pikvm_msd.py
pikvm_lib/pikvm_streamer.py
pikvm_lib/pikvm_websocket.py
pikvm_lib/pikvm_aux/__init__.py
pikvm_lib/pikvm_aux/pikvm_aux.py
pikvm_lib/pikvm_aux/pikvm_endpoints_base.py
pikvm_lib-0.5.0.dist-info/licenses/LICENSE
pikvm_lib-0.5.0.dist-info/METADATA
pikvm_lib-0.5.0.dist-info/WHEEL
pikvm_lib-0.5.0.dist-info/top_level.txt
pikvm_lib-0.5.0.dist-info/RECORD
