Metadata-Version: 2.4
Name: pikvm_lib
Version: 0.5.0
Summary: Library to control PiKVM with Python
Author-email: guanana <guanana2@gmail.com>
License: GNU v3
Project-URL: Homepage, https://github.com/guanana/pikvm-lib
Project-URL: Issues, https://github.com/guanana/pikvm-lib/issues
Keywords: pikvm,pikvm-lib,kvm
Classifier: Development Status :: 4 - Beta
Classifier: Intended Audience :: Information Technology
Classifier: Programming Language :: Python :: 3
Classifier: License :: OSI Approved :: GNU Affero General Public License v3
Classifier: Operating System :: OS Independent
Classifier: Topic :: Software Development :: Libraries
Requires-Python: >=3.9
License-File: LICENSE
Requires-Dist: requests>=2.31.0
Requires-Dist: pyotp<=2.9.0
Requires-Dist: websocket-client>=1.7.0
Requires-Dist: pillow>=11.3.0
Dynamic: license-file
